Workbook

Sheet P-Raw
G2: PACKAGES MASTER TABLE
E3: Packages ID | F3: Package Name | G3: Category | H3: Duration | I3: Pricing Type | J3: $ Price /person | K3: Activities
E4: P001 | F4: Magic in the Skies-HoneyMoon Retreat | G4: Couple | H4: 3 Days/2 Nights | I4: Fixed Per Package | J4: 800 | K4: Premium Cave Suite, Hot Air Balloon Ride, Love Valley Hike, Rooftop Breakfast
E5: P002 | F5: Golden Dawn Luxury Couples Escape | G5: Couple | H5: 3 Days/2 Nights | I5: Fixed Per Package | J5: 1500 | K5: Luxury Cave Villa, Private Jacuzzi & Rose Decor, Luxury Spa, Photoshoot
E6: P003 | F6: Adventure Discovery – Family | G6: Family | H6: 5 Days/4 Nights | I6: Per Person | J6: 550 | K6: Cave Suite, Sword Valley Hike, Horse Safari, ATV Sunset Ride, Turkish Cultural Night, Pottery Workshop
E7: P004 | F7: Ride & Rise Combo – Adventure | G7: Adventure | H7: 2 Days/1 Nights | I7: Per Person | J7: 480 | K7: Standard Cave Room, Göreme Town Tour, Jeep Safari, Paragliding, Horse Riding, Sunset Hot Air Balloon
E8: P005 | F8: Squad Goals Adventure Trip | G8: Friends | H8: 3 Days/2 Nights | I8: Per Person | J8: 450 | K8: Cave Suite, Jeep Safari, BBQ Night, Sunrise Viewpoint, Photo Spots Tour
E9: P006 | F9: Cappadocia Relaxation & Wellness Retreat | G9: Wellness | H9: 4 Days/3 Nights | I9: Per Person | J9: 990 | K9: Premium Cave Suite, Cave Spa Hotel, Turkish Hammam, Yoga & Meditation, Relaxation Valley Tour

Sheet P-Booking
A1: o
F9: PACKAGES BOOKING TABLE
C10: Booking ID | D10: Packages ID | E10: Package Name | F10: Package Type | G10: Persons | H10: $Price per Person | I10: $Total Cost | J10: Payment Status
C11: BP001 | D11: P001 | E11: Magic in the Skies-HoneyMoon Retreat | F11: Couple | G11: 2 | H11: _ | I11: 800 | J11: YES
C12: BP002 | D12: P002 | E12: Golden Dawn Luxury Couples Escape | F12: couple | G12: 2 | H12: _ | I12: 1500 | J12: YES
C13: BP003 | D13: P001 | E13: Magic in the Skies-HoneyMoon Retreat | F13: Couple | G13: 2 | H13: _ | I13: 800 | J13: NO
C14: BP004 | D14: P003 | E14: Adventure Discovery – Family | F14: Family | G14: 4 | H14: 550 | I14: =(H14*G14) -> 2200 | J14: YES
C15: BP005 | D15: P004 | E15: Ride & Rise Combo – Adventure | F15: Adventure | G15: 3 | H15: 480 | I15: =(H15*G15) -> 1440 | J15: NO
C16: BP006 | D16: P005 | E16: Squad Goals Adventure Trip | F16: Friends | G16: 5 | H16: 450 | I16: =(H16*G16) -> 2250 | J16: YES
C17: BP007 | D17: P003 | E17: Adventure Discovery – Family | F17: Family | G17: 4 | H17: 550 | I17: =(H17*G17) -> 2200 | J17: YES
C18: BP008 | D18: P001 | E18: Magic in the Skies-HoneyMoon Retreat | F18: Couple | G18: 2 | H18: _ | I18: 800 | J18: NO
C19: BP009 | D19: P006 | E19: Cappadocia Relaxation & Wellness Retreat | F19: Wellness | G19: 1 | H19: 990 | I19: =(H19*G19) -> 990 | J19: YES
C20: BP010 | D20: P002 | E20: Golden Dawn Luxury Couple Escape | F20: Couple | G20: 2 | H20: _ | I20: 1500 | J20: YES
C21: BP011 | D21: P004 | E21: Ride & Rise Combo – Adventure | F21: Adventure | G21: 3 | H21: 480 | I21: =(H21*G21) -> 1440 | J21: YES
C22: BP012 | D22: P006 | E22: Cappadocia Relaxation & Wellness Retreat | F22: Wellness | G22: 1 | H22: 990 | I22: =(H22*G22) -> 990 | J22: NO

Sheet P-Summary
G5: SUMMARY TABLE
D6: Package ID | E6: Package Name | F6: Price(per person) | G6: Total Bookings | H6: Persons per Booking | I6: $ Total Revenue
D7: P001 | E7: Magic in the Skies-Couple | F7: 800 | G7: =COUNTIF('P-Booking'!$D$11:$D$22, D7) -> 3 | H7: 1 | I7: =(F7*G7*H7) -> 2400
D8: P002 | E8: Golden Dawn Luxury Couple Escape | F8: 1500 | G8: =COUNTIF('P-Booking'!$D$11:$D$22, D8) -> 2 | H8: 1 | I8: =(F8*G8*H8) -> 3000
D9: P003 | E9: Adventure Discovery – Family | F9: 550 | G9: =COUNTIF('P-Booking'!$D$11:$D$22, D9) -> 2 | H9: 4 | I9: =(F9*G9*H9) -> 4400
D10: P004 | E10: Ride & Rise Combo – Adventure | F10: 480 | G10: =COUNTIF('P-Booking'!$D$11:$D$22, D10) -> 2 | H10: 3 | I10: =(F10*G10*H10) -> 2880
D11: P005 | E11: Squad Goals Adventure Trip | F11: 450 | G11: =COUNTIF('P-Booking'!$D$11:$D$23, D11) -> 1 | H11: 5 | I11: =(F11*G11*H11) -> 2250
D12: P006 | E12: Cappadocia Relaxation & Wellness Retreat | F12: 990 | G12: =COUNTIF('P-Booking'!$D$11:$D$22, D12) -> 2 | H12: 1 | I12: =(F12*G12*H12) -> 1980
H13: TOTAL | I13: =SUM(I7:I12) -> 16910
F14: TOTAL REVENUE= $16910

Sheet R-Raw
K3: ROOM'S TABLE
G4: Room ID | H4: Room Name | I4: Size(m²) | J4: Max Guests | K4: Price per Night($) | L4: Total Rooms | M4: Booked Rooms | N4: Available Rooms | O4: Notes
G5: R001 | H5: Standard Cave Room | I5: 20–35 | J5: 2 | K5: 120 | L5: 10 | M5: 4 | N5: =L5-M5 -> 6 | O5: Fireplace optional
G6: R002 | H6: Deluxe Cave Room | I6: 30–45 | J6: 3 | K6: 250 | L6: 8 | M6: 3 | N6: =L6-M6 -> 5 | O6: Spacious, stone interior
G7: R003 | H7: Cave Suite | I7: 45–65 | J7: 4 | K7: 370 | L7: 5 | M7: 3 | N7: =L7-M7 -> 2 | O7: Separate living area
G8: R004 | H8: Premium Cave Suite | I8: 50–70 | J8: 4 | K8: 450 | L8: 3 | M8: 1 | N8: =L8-M8 -> 2 | O8: Panoramic views
G9: R005 | H9: Luxury Cave Villa | I9: 60–80 | J9: 5 | K9: 560 | L9: 3 | M9: 2 | N9: =L9-M9 -> 1 | O9: Private terrace

Sheet R-Booking
I4: ROOM'S BOOKING TABLE
G5: Booking ID | H5: Room ID | I5: Nights | J5: $ Total Cost | K5: Payment Status
G6: BR001 | H6: R001 | I6: 3 | J6: =('R-Raw'!K5*I6) -> 360 | K6: YES
G7: BR002 | H7: R002 | I7: 2 | J7: =('R-Raw'!K6*I7) -> 500 | K7: YES
G8: BR003 | H8: R001 | I8: 3 | J8: =('R-Raw'!K5*I8) -> 360 | K8: NO
G9: BR004 | H9: R004 | I9: 5 | J9: =('R-Raw'!K8*I9) -> 2250 | K9: YES
G10: BR005 | H10: R003 | I10: 3 | J10: =('R-Raw'!K7*I10) -> 1110 | K10: YES
G11: BR006 | H11: R002 | I11: 2 | J11: =('R-Raw'!K6*I11) -> 500 | K11: NO
G12: BR007 | H12: R003 | I12: 3 | J12: =(I12*'R-Raw'!K7) -> 1110 | K12: NO
G13: BR008 | H13: R005 | I13: 3 | J13: =(I13*'R-Raw'!K9) -> 1680 | K13: YES
G14: BR009 | H14: R001 | I14: 3 | J14: =(I14*'R-Raw'!K5) -> 360 | K14: YES
G15: BR010 | H15: R002 | I15: 2 | J15: =(I15*'R-Raw'!K6) -> 500 | K15: YES
G16: BR011 | H16: R001 | I16: 3 | J16: =(I16*'R-Raw'!K5) -> 360 | K16: YES
G17: BR012 | H17: R003 | I17: 3 | J17: =(I17*'R-Raw'!K7) -> 1110 | K17: YES
G18: BR013 | H18: R005 | I18: 3 | J18: =(I18*'R-Raw'!K9) -> 1680 | K18: NO

Sheet R-Summary
H4: SUMMARY TABLE
E5: Room ID | F5: Room Name | G5: Total Rooms | H5: Booked Rooms | I5: Available Rooms | J5: Price per Night | K5: Total Nights | L5: $ Total Revenue
E6: R001 | F6: Standard Cave Room | G6: 10 | H6: 4 | I6: =(G6-H6) -> 6 | J6: 120 | K6: =(4*3) -> 12 | L6: =(J6*K6) -> 1440
E7: R002 | F7: Deluxe Cave Room | G7: 8 | H7: 3 | I7: =(G7-H7) -> 5 | J7: 250 | K7: =(3*2) -> 6 | L7: =(J7*K7) -> 1500
E8: R003 | F8: Cave Suite | G8: 5 | H8: 3 | I8: =(G8-H8) -> 2 | J8: 370 | K8: =(3*3) -> 9 | L8: =(J8*K8) -> 3330
E9: R004 | F9: Premium Cave Suite | G9: 3 | H9: 1 | I9: =(G9-H9) -> 2 | J9: 450 | K9: =(1*5) -> 5 | L9: =(J9*K9) -> 2250
E10: R005 | F10: Luxury Cave Villa | G10: 3 | H10: 2 | I10: =(G10-H10) -> 1 | J10: 560 | K10: =(3*2) -> 6 | L10: =(J10*K10) -> 3360
K11: Total | L11: =SUM(L6:L10) -> 11880
G12: TOTAL BOOKED ROOMS = 13
G13: TOTAL NIGHTS =38
G14: TOTAL ROOMS REVENUE= $11880

Sheet P-R-Schedule
H4: P-R-BOOKING SCHEDULE
E6: Resource ID | F6: 45658 | G6: 45659 | H6: 45660 | I6: 45661 | J6: 45662 | K6: 45663 | L6: 45664
E7: ROOMS
E8: R001 | F8: BR001 | G8: BR001 | H8: BR001 | I8: BR009 | J8: BR009 | K8: BR009
E9: R002 | G9: BR002 | H9: BR002 | K9: BR006 | L9: BR006
E10: R003 | F10: BR005 | G10: BR005 | H10: BR005 | J10: BR007 | K10: BR007 | L10: BR007
E11: R004 | F11: BR004 | G11: BR004 | H11: BR004 | I11: BR004 | J11: BR004
E12: R005 | I12: BR013 | J12: BR013 | K12: BR013
E14: PACKAGES
E15: P001-honeymoon | F15: BP001 | G15: BP001 | H15: BP001 | J15: BP008 | K15: BP008 | L15: BP008
E16: P002-Couple | I16: BP002 | J16: BP002 | K16: BP002
E17: P003-Family | F17: BP007 | G17: BP007 | H17: BP007 | I17: BP007 | J17: BP007
E18: P004-Adventure | H18: BP011 | I18: BP011 | K18: BP005 | L18: BP005
E19: P005-Friends | F19: BP006 | G19: BP006 | H19: BP006
E20: P006-Wellness | I20: BP009 | J20: BP009 | K20: BP009 | L20: BP009

Sheet Total-Revenue
D2: TOTAL REVENUE
D3: ID | E3: Type | F3: $ Total Revenue
D4: P001 | E4: Package | F4: 2400
D5: P002 | E5: Package | F5: 3000
D6: P003 | E6: Package | F6: 4400
D7: P004 | E7: Package | F7: 2880
D8: P005 | E8: Package | F8: 2250
D9: P006 | E9: Package | F9: 1980
D10: R001 | E10: Room | F10: 1440
D11: R002 | E11: Room | F11: 1500
D12: R003 | E12: Room | F12: 3330
D13: R004 | E13: Room | F13: 2250
D14: R005 | E14: Room | F14: 3360
E16: TOTAL | F16: =SUM(F4:F14) -> 28790
D18: $ PACKAGES REVENUE | E18: =SUM(F4:F9) -> 16910
D19: $ ROOM'S REVENUE | E19: =SUM(F10:F14) -> 11880
